gcalcli/__init__.py
gcalcli/_types.py
gcalcli/_version.py
gcalcli/actions.py
gcalcli/argparsers.py
gcalcli/auth.py
gcalcli/cli.py
gcalcli/config.py
gcalcli/conflicts.py
gcalcli/deprecations.py
gcalcli/details.py
gcalcli/env.py
gcalcli/exceptions.py
gcalcli/gcal.py
gcalcli/ics.py
gcalcli/printer.py
gcalcli/utils.py
gcalcli/validators.py
gcalcli-4.5.1.data/data/share/man/man1/gcalcli.1
gcalcli-4.5.1.dist-info/LICENSE
gcalcli-4.5.1.dist-info/METADATA
gcalcli-4.5.1.dist-info/WHEEL
gcalcli-4.5.1.dist-info/entry_points.txt
gcalcli-4.5.1.dist-info/top_level.txt
gcalcli-4.5.1.dist-info/RECORD
