Metadata-Version: 2.1
Name: gcalcli
Version: 4.5.1
Summary: Google Calendar Command Line Interface
Author: Eric Davis, Brian Hartvigsen, Joshua Crowgey
Maintainer: David Barnett, Martin Dengler
License: MIT
Project-URL: Repository, https://github.com/insanum/gcalcli
Project-URL: Issues, https://github.com/insanum/gcalcli/issues
Project-URL: Changelog, https://github.com/insanum/gcalcli/blob/HEAD/ChangeLog
Classifier: Development Status :: 5 - Production/Stable
Classifier: Environment :: Console
Classifier: Intended Audience :: End Users/Desktop
Classifier: License :: OSI Approved :: MIT License
Classifier: Programming Language :: Python :: 3
Requires-Python: >=3.10
License-File: LICENSE
Requires-Dist: argcomplete
Requires-Dist: babel
Requires-Dist: google-api-python-client>=1.4
Requires-Dist: google_auth_oauthlib
Requires-Dist: httplib2
Requires-Dist: parsedatetime
Requires-Dist: platformdirs
Requires-Dist: pydantic
Requires-Dist: python-dateutil
Requires-Dist: tomli; python_version < "3.11"
Requires-Dist: truststore
Provides-Extra: dev
Requires-Dist: google-api-python-client-stubs; extra == "dev"
Requires-Dist: types-python-dateutil; extra == "dev"
Requires-Dist: types-requests; extra == "dev"
Requires-Dist: types-toml; python_version < "3.11" and extra == "dev"
Requires-Dist: types-vobject; extra == "dev"
Provides-Extra: vobject
Requires-Dist: vobject; extra == "vobject"
